obsidian/__init__.py
obsidian/events.py
obsidian/exceptions.py
obsidian/filters.py
obsidian/node.py
obsidian/objects.py
obsidian/player.py
obsidian/pool.py
obsidian/utils.py
obsidianpy-1.0.6.2.dist-info/LICENSE
obsidianpy-1.0.6.2.dist-info/METADATA
obsidianpy-1.0.6.2.dist-info/WHEEL
obsidianpy-1.0.6.2.dist-info/top_level.txt
obsidianpy-1.0.6.2.dist-info/RECORD
