Metadata-Version: 2.1
Name: obsidianpy
Version: 1.0.6.2
Summary: A discord.py ready wrapper for the audio sending node, Obsidian
Home-page: https://github.com/cloudwithax/obsidian.py
Author: cloudwithax
License: GPL
Keywords: obsidian,obsidian.py,discord.py
Platform: UNKNOWN
Classifier: Framework :: AsyncIO
Classifier: Operating System :: OS Independent
Classifier: Natural Language :: English
Classifier: Intended Audience :: Developers
Classifier: Programming Language :: Python :: 3 :: Only
Classifier: Programming Language :: Python :: 3.8
Classifier: Topic :: Software Development :: Libraries :: Python Modules
Classifier: Topic :: Software Development :: Libraries
Classifier: Topic :: Internet
Requires-Python: >=3.8
License-File: LICENSE
Requires-Dist: discord.py (>=1.7.1)
